{
	"monster": [
		{
			"name": "死亡化身", "ENG_name": "Avatar of Death",
			"size": "M",
			"type": "undead",
			"source": "DMG",
			"alignment": [
				"L",
				"E"
			],
			"ac": [
				20
			],
			"hp": {
				"special": "其召唤者生命值最大值的一半"
			},
			"speed": {
				"walk": 60,
				"fly": {
					"number": 60,
					"condition": "(浮空)"
				},
				"canHover": true
			},
			"str": 16,
			"dex": 16,
			"con": 16,
			"int": 16,
			"wis": 16,
			"cha": 16,
			"immune": [
				"necrotic",
				"poison"
			],
			"conditionImmune": [
				"charmed",
				"frightened",
				"paralyzed",
				"petrified",
				"poisoned",
				"unconscious"
			],
			"senses": "黑暗视觉60呎, 真实视觉60呎",
			"passive": 13,
			"languages": "所有其召唤者所知的语言",
			"cr": "Unknown",
			"trait": [
				{
					"name": "虚体移动", "tENG_name": "Incorporeal Movement",
					"entries": [
						"死亡化身可以把其它生物和物体视作困难地形移动穿过它们。若它在一个物体内结束它的回合，则它将受到5 ({@damage 1d10})力场伤害。"
					]
				},
				{
					"name": "驱散免疫", "tENG_name": "Turn Immunity",
					"entries": [
						"死亡化身免疫于驱散不死的效果。"
					]
				}
			],
			"action": [
				{
					"name": "收割之镰", "tENG_name": "Reaping Scythe",
					"entries": [
						"死亡化身将它的灵体大镰横扫穿过一个距离它5呎内的生物，造成 7 ({@damage 1d8 + 3})劈砍伤害加上 4 ({@damage 1d8})死灵伤害。"
					]
				}
			],
			"page": 164,
			"traitTags": [
				"Incorporeal Movement",
				"Turn Immunity"
			],
			"languageTags": [
				"XX"
			],
			"senseTags": [
				"D",
				"U"
			],
			"damageTags": [
				"S",
				"N",
				"O"
			]
		},
		{
			"name": "巨苍蝇", "ENG_name": "Giant Fly",
			"size": "L",
			"type": "beast",
			"source": "DMG",
			"alignment": [
				"U"
			],
			"ac": [
				11
			],
			"hp": {
				"average": 19,
				"formula": "3d10 + 3"
			},
			"speed": {
				"walk": 30,
				"fly": 60
			},
			"str": 14,
			"dex": 13,
			"con": 13,
			"int": 2,
			"wis": 10,
			"cha": 3,
			"senses": "黑暗视觉60呎",
			"passive": 10,
			"cr": "0",
			"page": 169,
			"senseTags": [
				"D"
			]
		},
		{
			"source": "DMG",
			"name": "堕魂幼虫", "ENG_name": "Larva",
			"size": "M",
			"type": "fiend",
			"alignment": [
				"L",
				"E"
			],
			"ac": [
				9
			],
			"hp": {
				"average": 9,
				"formula": "2d8"
			},
			"speed": {
				"walk": 20
			},
			"str": 9,
			"dex": 9,
			"con": 10,
			"int": 6,
			"wis": 10,
			"cha": 2,
			"passive": 10,
			"languages": "理解它生前所知的语言，但不会说",
			"cr": "0",
			"action": [
				{
					"name": "啃咬", "tENG_name": "Bite",
					"entries": [
						"{@atk mw} 命中{@hit 1}，触及5呎，单一目标。{@h}1 ({@damage 1d4 - 1})穿刺伤害。"
					]
				}
			],
			"page": 63,
			"languageTags": [
				"CS"
			],
			"damageTags": [
				"P"
			]
		}
	]
}
